[
  {
    "_index": "packets-2024-09-12",
    "_type": "doc",
    "_score": null,
    "_source": {
      "layers": {
        "frame": {
          "frame.encap_type": "1",
          "frame.time": "Sep 12, 2024 16:46:02.001703000 W. Europe Daylight Time",
          "frame.time_utc": "Sep 12, 2024 14:46:02.001703000 UTC",
          "frame.time_epoch": "1726152362.001703000",
          "frame.offset_shift": "0.000000000",
          "frame.time_delta": "0.000250000",
          "frame.time_delta_displayed": "0.000000000",
          "frame.time_relative": "1.774813000",
          "frame.number": "143",
          "frame.len": "80",
          "frame.cap_len": "80",
          "frame.marked": "0",
          "frame.ignored": "0",
          "frame.protocols": "eth:ethertype:ip:tcp:doip:uds",
          "frame.coloring_rule.name": "TCP",
          "frame.coloring_rule.string": "tcp"
        },
        "eth": {
          "eth.dst": "00:00:00:00:00:00",
          "eth.dst_tree": {
            "eth.dst_resolved": "00:00:00_00:00:00",
            "eth.dst.oui": "0",
            "eth.dst.oui_resolved": "Officially Xerox, but 0:0:0:0:0:0 is more common",
            "eth.dst.lg": "0",
            "eth.dst.ig": "0",
            "eth.addr": "00:00:00:00:00:00",
            "eth.addr_resolved": "00:00:00_00:00:00",
            "eth.addr.oui": "0",
            "eth.addr.oui_resolved": "Officially Xerox, but 0:0:0:0:0:0 is more common",
            "eth.lg": "0",
            "eth.ig": "0"
          },
          "eth.src": "00:00:00:00:00:00",
          "eth.src_tree": {
            "eth.src_resolved": "00:00:00_00:00:00",
            "eth.src.oui": "0",
            "eth.src.oui_resolved": "Officially Xerox, but 0:0:0:0:0:0 is more common",
            "eth.src.lg": "0",
            "eth.src.ig": "0",
            "eth.addr": "00:00:00:00:00:00",
            "eth.addr_resolved": "00:00:00_00:00:00",
            "eth.addr.oui": "0",
            "eth.addr.oui_resolved": "Officially Xerox, but 0:0:0:0:0:0 is more common",
            "eth.lg": "0",
            "eth.ig": "0"
          },
          "eth.type": "0x0800",
          "eth.stream": "0"
        },
        "ip": {
          "ip.version": "4",
          "ip.hdr_len": "20",
          "ip.dsfield": "0x00",
          "ip.dsfield_tree": {
            "ip.dsfield.dscp": "0",
            "ip.dsfield.ecn": "0"
          },
          "ip.len": "66",
          "ip.id": "0x3bf3",
          "ip.flags": "0x02",
          "ip.flags_tree": {
            "ip.flags.rb": "0",
            "ip.flags.df": "1",
            "ip.flags.mf": "0"
          },
          "ip.frag_offset": "0",
          "ip.ttl": "64",
          "ip.proto": "6",
          "ip.checksum": "0x00c1",
          "ip.checksum.status": "1",
          "ip.checksum_calculated": "0x00c1",
          "ip.src": "127.0.0.1",
          "ip.addr": "127.0.0.1",
          "ip.src_host": "kubernetes.docker.internal",
          "ip.host": "kubernetes.docker.internal",
          "ip.dst": "127.0.0.1",
          "ip.addr": "127.0.0.1",
          "ip.dst_host": "kubernetes.docker.internal",
          "ip.host": "kubernetes.docker.internal",
          "ip.stream": "0"
        },
        "tcp": {
          "tcp.srcport": "43208",
          "tcp.dstport": "13400",
          "tcp.port": "43208",
          "tcp.port": "13400",
          "tcp.stream": "2",
          "tcp.stream.pnum": "8",
          "tcp.completeness": "31",
          "tcp.completeness_tree": {
            "tcp.completeness.rst": "0",
            "tcp.completeness.fin": "1",
            "tcp.completeness.data": "1",
            "tcp.completeness.ack": "1",
            "tcp.completeness.syn-ack": "1",
            "tcp.completeness.syn": "1",
            "tcp.completeness.str": "·FDASS"
          },
          "tcp.len": "14",
          "tcp.seq": "3549143258",
          "tcp.seq_raw": "3549143258",
          "tcp.nxtseq": "3549143272",
          "tcp.ack": "1622714211",
          "tcp.ack_raw": "1622714211",
          "tcp.hdr_len": "32",
          "tcp.flags": "0x0018",
          "tcp.flags_tree": {
            "tcp.flags.res": "0",
            "tcp.flags.ae": "0",
            "tcp.flags.cwr": "0",
            "tcp.flags.ece": "0",
            "tcp.flags.urg": "0",
            "tcp.flags.ack": "1",
            "tcp.flags.push": "1",
            "tcp.flags.reset": "0",
            "tcp.flags.syn": "0",
            "tcp.flags.fin": "0",
            "tcp.flags.str": "·······AP···"
          },
          "tcp.window_size_value": "512",
          "tcp.window_size": "65536",
          "tcp.window_size_scalefactor": "128",
          "tcp.checksum": "0xfe36",
          "tcp.checksum.status": "2",
          "tcp.urgent_pointer": "0",
          "tcp.options": "01:01:08:0a:cd:d9:d7:23:cd:d9:d7:20",
          "tcp.options_tree": {
            "tcp.options.nop": "01",
            "tcp.options.nop_tree": {
              "tcp.option_kind": "1"
            },
            "tcp.options.nop": "01",
            "tcp.options.nop_tree": {
              "tcp.option_kind": "1"
            },
            "tcp.options.timestamp": "08:0a:cd:d9:d7:23:cd:d9:d7:20",
            "tcp.options.timestamp_tree": {
              "tcp.option_kind": "8",
              "tcp.option_len": "10",
              "tcp.options.timestamp.tsval": "3453605667",
              "tcp.options.timestamp.tsecr": "3453605664"
            }
          },
          "Timestamps": {
            "tcp.time_relative": "0.013540000",
            "tcp.time_delta": "0.002527000"
          },
          "tcp.payload": "02:fd:80:01:00:00:00:06:0e:00:10:32:3e:00",
          "tcp.pdu.size": "14"
        },
        "doip": {
          "Header": {
            "doip.version": "0x02",
            "doip.inverse": "0xfd",
            "doip.type": "0x8001",
            "doip.length": "6"
          },
          "doip.source_address": "0x0e00",
          "doip.target_address": "0x1032"
        },
        "uds": {
          "uds.diag_addr_source": "0x0e00",
          "uds.diag_addr_source_name": "3584",
          "uds.diag_addr": "0x0e00",
          "uds.diag_addr_name": "3584",
          "uds.diag_addr_target": "0x1032",
          "uds.diag_addr_target_name": "4146",
          "uds.diag_addr": "0x1032",
          "uds.diag_addr_name": "4146",
          "uds.sid": "0x3e",
          "uds.reply": "0x00",
          "uds.subfunction": "0x00",
          "uds.subfunction_tree": {
            "uds.tp.subfunction_without_suppress": "0x00",
            "uds.suppress_reply.indication": "0"
          }
        }
      }
    }
  },
  {
    "_index": "packets-2024-09-12",
    "_type": "doc",
    "_score": null,
    "_source": {
      "layers": {
        "frame": {
          "frame.encap_type": "1",
          "frame.time": "Sep 12, 2024 16:46:02.005863000 W. Europe Daylight Time",
          "frame.time_utc": "Sep 12, 2024 14:46:02.005863000 UTC",
          "frame.time_epoch": "1726152362.005863000",
          "frame.offset_shift": "0.000000000",
          "frame.time_delta": "0.000024000",
          "frame.time_delta_displayed": "0.004160000",
          "frame.time_relative": "1.778973000",
          "frame.number": "148",
          "frame.len": "80",
          "frame.cap_len": "80",
          "frame.marked": "0",
          "frame.ignored": "0",
          "frame.protocols": "eth:ethertype:ip:tcp:doip:uds",
          "frame.coloring_rule.name": "TCP",
          "frame.coloring_rule.string": "tcp"
        },
        "eth": {
          "eth.dst": "00:00:00:00:00:00",
          "eth.dst_tree": {
            "eth.dst_resolved": "00:00:00_00:00:00",
            "eth.dst.oui": "0",
            "eth.dst.oui_resolved": "Officially Xerox, but 0:0:0:0:0:0 is more common",
            "eth.dst.lg": "0",
            "eth.dst.ig": "0",
            "eth.addr": "00:00:00:00:00:00",
            "eth.addr_resolved": "00:00:00_00:00:00",
            "eth.addr.oui": "0",
            "eth.addr.oui_resolved": "Officially Xerox, but 0:0:0:0:0:0 is more common",
            "eth.lg": "0",
            "eth.ig": "0"
          },
          "eth.src": "00:00:00:00:00:00",
          "eth.src_tree": {
            "eth.src_resolved": "00:00:00_00:00:00",
            "eth.src.oui": "0",
            "eth.src.oui_resolved": "Officially Xerox, but 0:0:0:0:0:0 is more common",
            "eth.src.lg": "0",
            "eth.src.ig": "0",
            "eth.addr": "00:00:00:00:00:00",
            "eth.addr_resolved": "00:00:00_00:00:00",
            "eth.addr.oui": "0",
            "eth.addr.oui_resolved": "Officially Xerox, but 0:0:0:0:0:0 is more common",
            "eth.lg": "0",
            "eth.ig": "0"
          },
          "eth.type": "0x0800",
          "eth.stream": "0"
        },
        "ip": {
          "ip.version": "4",
          "ip.hdr_len": "20",
          "ip.dsfield": "0x00",
          "ip.dsfield_tree": {
            "ip.dsfield.dscp": "0",
            "ip.dsfield.ecn": "0"
          },
          "ip.len": "66",
          "ip.id": "0x4cc1",
          "ip.flags": "0x02",
          "ip.flags_tree": {
            "ip.flags.rb": "0",
            "ip.flags.df": "1",
            "ip.flags.mf": "0"
          },
          "ip.frag_offset": "0",
          "ip.ttl": "64",
          "ip.proto": "6",
          "ip.checksum": "0xeff2",
          "ip.checksum.status": "1",
          "ip.checksum_calculated": "0xeff2",
          "ip.src": "127.0.0.1",
          "ip.addr": "127.0.0.1",
          "ip.src_host": "kubernetes.docker.internal",
          "ip.host": "kubernetes.docker.internal",
          "ip.dst": "127.0.0.1",
          "ip.addr": "127.0.0.1",
          "ip.dst_host": "kubernetes.docker.internal",
          "ip.host": "kubernetes.docker.internal",
          "ip.stream": "0"
        },
        "tcp": {
          "tcp.srcport": "13400",
          "tcp.dstport": "43208",
          "tcp.port": "13400",
          "tcp.port": "43208",
          "tcp.stream": "2",
          "tcp.stream.pnum": "10",
          "tcp.completeness": "31",
          "tcp.completeness_tree": {
            "tcp.completeness.rst": "0",
            "tcp.completeness.fin": "1",
            "tcp.completeness.data": "1",
            "tcp.completeness.ack": "1",
            "tcp.completeness.syn-ack": "1",
            "tcp.completeness.syn": "1",
            "tcp.completeness.str": "·FDASS"
          },
          "tcp.len": "14",
          "tcp.seq": "1622714224",
          "tcp.seq_raw": "1622714224",
          "tcp.nxtseq": "1622714238",
          "tcp.ack": "3549143272",
          "tcp.ack_raw": "3549143272",
          "tcp.hdr_len": "32",
          "tcp.flags": "0x0018",
          "tcp.flags_tree": {
            "tcp.flags.res": "0",
            "tcp.flags.ae": "0",
            "tcp.flags.cwr": "0",
            "tcp.flags.ece": "0",
            "tcp.flags.urg": "0",
            "tcp.flags.ack": "1",
            "tcp.flags.push": "1",
            "tcp.flags.reset": "0",
            "tcp.flags.syn": "0",
            "tcp.flags.fin": "0",
            "tcp.flags.str": "·······AP···"
          },
          "tcp.window_size_value": "512",
          "tcp.window_size": "65536",
          "tcp.window_size_scalefactor": "128",
          "tcp.checksum": "0xfe36",
          "tcp.checksum.status": "2",
          "tcp.urgent_pointer": "0",
          "tcp.options": "01:01:08:0a:cd:d9:d7:27:cd:d9:d7:23",
          "tcp.options_tree": {
            "tcp.options.nop": "01",
            "tcp.options.nop_tree": {
              "tcp.option_kind": "1"
            },
            "tcp.options.nop": "01",
            "tcp.options.nop_tree": {
              "tcp.option_kind": "1"
            },
            "tcp.options.timestamp": "08:0a:cd:d9:d7:27:cd:d9:d7:23",
            "tcp.options.timestamp_tree": {
              "tcp.option_kind": "8",
              "tcp.option_len": "10",
              "tcp.options.timestamp.tsval": "3453605671",
              "tcp.options.timestamp.tsecr": "3453605667"
            }
          },
          "Timestamps": {
            "tcp.time_relative": "0.017700000",
            "tcp.time_delta": "0.002460000"
          },
          "tcp.payload": "02:fd:80:01:00:00:00:06:10:32:0e:00:7e:00",
          "tcp.pdu.size": "14"
        },
        "doip": {
          "Header": {
            "doip.version": "0x02",
            "doip.inverse": "0xfd",
            "doip.type": "0x8001",
            "doip.length": "6"
          },
          "doip.source_address": "0x1032",
          "doip.target_address": "0x0e00"
        },
        "uds": {
          "uds.diag_addr_source": "0x1032",
          "uds.diag_addr_source_name": "4146",
          "uds.diag_addr": "0x1032",
          "uds.diag_addr_name": "4146",
          "uds.diag_addr_target": "0x0e00",
          "uds.diag_addr_target_name": "3584",
          "uds.diag_addr": "0x0e00",
          "uds.diag_addr_name": "3584",
          "uds.sid": "0x3e",
          "uds.reply": "0x01",
          "uds.subfunction": "0x00",
          "uds.subfunction_tree": {
            "uds.tp.subfunction_without_suppress": "0x00"
          }
        }
      }
    }
  },
  {
    "_index": "packets-2024-09-12",
    "_type": "doc",
    "_score": null,
    "_source": {
      "layers": {
        "frame": {
          "frame.encap_type": "1",
          "frame.time": "Sep 12, 2024 16:46:02.006007000 W. Europe Daylight Time",
          "frame.time_utc": "Sep 12, 2024 14:46:02.006007000 UTC",
          "frame.time_epoch": "1726152362.006007000",
          "frame.offset_shift": "0.000000000",
          "frame.time_delta": "0.000113000",
          "frame.time_delta_displayed": "0.000144000",
          "frame.time_relative": "1.779117000",
          "frame.number": "150",
          "frame.len": "80",
          "frame.cap_len": "80",
          "frame.marked": "0",
          "frame.ignored": "0",
          "frame.protocols": "eth:ethertype:ip:tcp:doip:uds",
          "frame.coloring_rule.name": "TCP",
          "frame.coloring_rule.string": "tcp"
        },
        "eth": {
          "eth.dst": "00:00:00:00:00:00",
          "eth.dst_tree": {
            "eth.dst_resolved": "00:00:00_00:00:00",
            "eth.dst.oui": "0",
            "eth.dst.oui_resolved": "Officially Xerox, but 0:0:0:0:0:0 is more common",
            "eth.dst.lg": "0",
            "eth.dst.ig": "0",
            "eth.addr": "00:00:00:00:00:00",
            "eth.addr_resolved": "00:00:00_00:00:00",
            "eth.addr.oui": "0",
            "eth.addr.oui_resolved": "Officially Xerox, but 0:0:0:0:0:0 is more common",
            "eth.lg": "0",
            "eth.ig": "0"
          },
          "eth.src": "00:00:00:00:00:00",
          "eth.src_tree": {
            "eth.src_resolved": "00:00:00_00:00:00",
            "eth.src.oui": "0",
            "eth.src.oui_resolved": "Officially Xerox, but 0:0:0:0:0:0 is more common",
            "eth.src.lg": "0",
            "eth.src.ig": "0",
            "eth.addr": "00:00:00:00:00:00",
            "eth.addr_resolved": "00:00:00_00:00:00",
            "eth.addr.oui": "0",
            "eth.addr.oui_resolved": "Officially Xerox, but 0:0:0:0:0:0 is more common",
            "eth.lg": "0",
            "eth.ig": "0"
          },
          "eth.type": "0x0800",
          "eth.stream": "0"
        },
        "ip": {
          "ip.version": "4",
          "ip.hdr_len": "20",
          "ip.dsfield": "0x00",
          "ip.dsfield_tree": {
            "ip.dsfield.dscp": "0",
            "ip.dsfield.ecn": "0"
          },
          "ip.len": "66",
          "ip.id": "0x3bf5",
          "ip.flags": "0x02",
          "ip.flags_tree": {
            "ip.flags.rb": "0",
            "ip.flags.df": "1",
            "ip.flags.mf": "0"
          },
          "ip.frag_offset": "0",
          "ip.ttl": "64",
          "ip.proto": "6",
          "ip.checksum": "0x00bf",
          "ip.checksum.status": "1",
          "ip.checksum_calculated": "0x00bf",
          "ip.src": "127.0.0.1",
          "ip.addr": "127.0.0.1",
          "ip.src_host": "kubernetes.docker.internal",
          "ip.host": "kubernetes.docker.internal",
          "ip.dst": "127.0.0.1",
          "ip.addr": "127.0.0.1",
          "ip.dst_host": "kubernetes.docker.internal",
          "ip.host": "kubernetes.docker.internal",
          "ip.stream": "0"
        },
        "tcp": {
          "tcp.srcport": "43208",
          "tcp.dstport": "13400",
          "tcp.port": "43208",
          "tcp.port": "13400",
          "tcp.stream": "2",
          "tcp.stream.pnum": "12",
          "tcp.completeness": "31",
          "tcp.completeness_tree": {
            "tcp.completeness.rst": "0",
            "tcp.completeness.fin": "1",
            "tcp.completeness.data": "1",
            "tcp.completeness.ack": "1",
            "tcp.completeness.syn-ack": "1",
            "tcp.completeness.syn": "1",
            "tcp.completeness.str": "·FDASS"
          },
          "tcp.len": "14",
          "tcp.seq": "3549143272",
          "tcp.seq_raw": "3549143272",
          "tcp.nxtseq": "3549143286",
          "tcp.ack": "1622714238",
          "tcp.ack_raw": "1622714238",
          "tcp.hdr_len": "32",
          "tcp.flags": "0x0018",
          "tcp.flags_tree": {
            "tcp.flags.res": "0",
            "tcp.flags.ae": "0",
            "tcp.flags.cwr": "0",
            "tcp.flags.ece": "0",
            "tcp.flags.urg": "0",
            "tcp.flags.ack": "1",
            "tcp.flags.push": "1",
            "tcp.flags.reset": "0",
            "tcp.flags.syn": "0",
            "tcp.flags.fin": "0",
            "tcp.flags.str": "·······AP···"
          },
          "tcp.window_size_value": "512",
          "tcp.window_size": "65536",
          "tcp.window_size_scalefactor": "128",
          "tcp.checksum": "0xfe36",
          "tcp.checksum.status": "2",
          "tcp.urgent_pointer": "0",
          "tcp.options": "01:01:08:0a:cd:d9:d7:27:cd:d9:d7:24",
          "tcp.options_tree": {
            "tcp.options.nop": "01",
            "tcp.options.nop_tree": {
              "tcp.option_kind": "1"
            },
            "tcp.options.nop": "01",
            "tcp.options.nop_tree": {
              "tcp.option_kind": "1"
            },
            "tcp.options.timestamp": "08:0a:cd:d9:d7:27:cd:d9:d7:24",
            "tcp.options.timestamp_tree": {
              "tcp.option_kind": "8",
              "tcp.option_len": "10",
              "tcp.options.timestamp.tsval": "3453605671",
              "tcp.options.timestamp.tsecr": "3453605668"
            }
          },
          "Timestamps": {
            "tcp.time_relative": "0.017844000",
            "tcp.time_delta": "0.000113000"
          },
          "tcp.payload": "02:fd:80:01:00:00:00:06:0e:00:10:32:3e:80",
          "tcp.pdu.size": "14"
        },
        "doip": {
          "Header": {
            "doip.version": "0x02",
            "doip.inverse": "0xfd",
            "doip.type": "0x8001",
            "doip.length": "6"
          },
          "doip.source_address": "0x0e00",
          "doip.target_address": "0x1032"
        },
        "uds": {
          "uds.diag_addr_source": "0x0e00",
          "uds.diag_addr_source_name": "3584",
          "uds.diag_addr": "0x0e00",
          "uds.diag_addr_name": "3584",
          "uds.diag_addr_target": "0x1032",
          "uds.diag_addr_target_name": "4146",
          "uds.diag_addr": "0x1032",
          "uds.diag_addr_name": "4146",
          "uds.sid": "0x3e",
          "uds.reply": "0x00",
          "uds.subfunction": "0x80",
          "uds.subfunction_tree": {
            "uds.tp.subfunction_without_suppress": "0x00",
            "uds.suppress_reply.indication": "1"
          }
        }
      }
    }
  },
  {
    "_index": "packets-2024-09-12",
    "_type": "doc",
    "_score": null,
    "_source": {
      "layers": {
        "frame": {
          "frame.encap_type": "1",
          "frame.time": "Sep 12, 2024 16:46:02.008942000 W. Europe Daylight Time",
          "frame.time_utc": "Sep 12, 2024 14:46:02.008942000 UTC",
          "frame.time_epoch": "1726152362.008942000",
          "frame.offset_shift": "0.000000000",
          "frame.time_delta": "0.001168000",
          "frame.time_delta_displayed": "0.002935000",
          "frame.time_relative": "1.782052000",
          "frame.number": "154",
          "frame.len": "80",
          "frame.cap_len": "80",
          "frame.marked": "0",
          "frame.ignored": "0",
          "frame.protocols": "eth:ethertype:ip:tcp:doip:uds",
          "frame.coloring_rule.name": "TCP",
          "frame.coloring_rule.string": "tcp"
        },
        "eth": {
          "eth.dst": "00:00:00:00:00:00",
          "eth.dst_tree": {
            "eth.dst_resolved": "00:00:00_00:00:00",
            "eth.dst.oui": "0",
            "eth.dst.oui_resolved": "Officially Xerox, but 0:0:0:0:0:0 is more common",
            "eth.dst.lg": "0",
            "eth.dst.ig": "0",
            "eth.addr": "00:00:00:00:00:00",
            "eth.addr_resolved": "00:00:00_00:00:00",
            "eth.addr.oui": "0",
            "eth.addr.oui_resolved": "Officially Xerox, but 0:0:0:0:0:0 is more common",
            "eth.lg": "0",
            "eth.ig": "0"
          },
          "eth.src": "00:00:00:00:00:00",
          "eth.src_tree": {
            "eth.src_resolved": "00:00:00_00:00:00",
            "eth.src.oui": "0",
            "eth.src.oui_resolved": "Officially Xerox, but 0:0:0:0:0:0 is more common",
            "eth.src.lg": "0",
            "eth.src.ig": "0",
            "eth.addr": "00:00:00:00:00:00",
            "eth.addr_resolved": "00:00:00_00:00:00",
            "eth.addr.oui": "0",
            "eth.addr.oui_resolved": "Officially Xerox, but 0:0:0:0:0:0 is more common",
            "eth.lg": "0",
            "eth.ig": "0"
          },
          "eth.type": "0x0800",
          "eth.stream": "0"
        },
        "ip": {
          "ip.version": "4",
          "ip.hdr_len": "20",
          "ip.dsfield": "0x00",
          "ip.dsfield_tree": {
            "ip.dsfield.dscp": "0",
            "ip.dsfield.ecn": "0"
          },
          "ip.len": "66",
          "ip.id": "0x4cc3",
          "ip.flags": "0x02",
          "ip.flags_tree": {
            "ip.flags.rb": "0",
            "ip.flags.df": "1",
            "ip.flags.mf": "0"
          },
          "ip.frag_offset": "0",
          "ip.ttl": "64",
          "ip.proto": "6",
          "ip.checksum": "0xeff0",
          "ip.checksum.status": "1",
          "ip.checksum_calculated": "0xeff0",
          "ip.src": "127.0.0.1",
          "ip.addr": "127.0.0.1",
          "ip.src_host": "kubernetes.docker.internal",
          "ip.host": "kubernetes.docker.internal",
          "ip.dst": "127.0.0.1",
          "ip.addr": "127.0.0.1",
          "ip.dst_host": "kubernetes.docker.internal",
          "ip.host": "kubernetes.docker.internal",
          "ip.stream": "0"
        },
        "tcp": {
          "tcp.srcport": "13400",
          "tcp.dstport": "43208",
          "tcp.port": "13400",
          "tcp.port": "43208",
          "tcp.stream": "2",
          "tcp.stream.pnum": "14",
          "tcp.completeness": "31",
          "tcp.completeness_tree": {
            "tcp.completeness.rst": "0",
            "tcp.completeness.fin": "1",
            "tcp.completeness.data": "1",
            "tcp.completeness.ack": "1",
            "tcp.completeness.syn-ack": "1",
            "tcp.completeness.syn": "1",
            "tcp.completeness.str": "·FDASS"
          },
          "tcp.len": "14",
          "tcp.seq": "1622714251",
          "tcp.seq_raw": "1622714251",
          "tcp.nxtseq": "1622714265",
          "tcp.ack": "3549143286",
          "tcp.ack_raw": "3549143286",
          "tcp.hdr_len": "32",
          "tcp.flags": "0x0018",
          "tcp.flags_tree": {
            "tcp.flags.res": "0",
            "tcp.flags.ae": "0",
            "tcp.flags.cwr": "0",
            "tcp.flags.ece": "0",
            "tcp.flags.urg": "0",
            "tcp.flags.ack": "1",
            "tcp.flags.push": "1",
            "tcp.flags.reset": "0",
            "tcp.flags.syn": "0",
            "tcp.flags.fin": "0",
            "tcp.flags.str": "·······AP···"
          },
          "tcp.window_size_value": "512",
          "tcp.window_size": "65536",
          "tcp.window_size_scalefactor": "128",
          "tcp.checksum": "0xfe36",
          "tcp.checksum.status": "2",
          "tcp.urgent_pointer": "0",
          "tcp.options": "01:01:08:0a:cd:d9:d7:2a:cd:d9:d7:27",
          "tcp.options_tree": {
            "tcp.options.nop": "01",
            "tcp.options.nop_tree": {
              "tcp.option_kind": "1"
            },
            "tcp.options.nop": "01",
            "tcp.options.nop_tree": {
              "tcp.option_kind": "1"
            },
            "tcp.options.timestamp": "08:0a:cd:d9:d7:2a:cd:d9:d7:27",
            "tcp.options.timestamp_tree": {
              "tcp.option_kind": "8",
              "tcp.option_len": "10",
              "tcp.options.timestamp.tsval": "3453605674",
              "tcp.options.timestamp.tsecr": "3453605671"
            }
          },
          "Timestamps": {
            "tcp.time_relative": "0.020779000",
            "tcp.time_delta": "0.002090000"
          },
          "tcp.payload": "02:fd:80:01:00:00:00:06:10:32:0e:00:7e:80",
          "tcp.pdu.size": "14"
        },
        "doip": {
          "Header": {
            "doip.version": "0x02",
            "doip.inverse": "0xfd",
            "doip.type": "0x8001",
            "doip.length": "6"
          },
          "doip.source_address": "0x1032",
          "doip.target_address": "0x0e00"
        },
        "uds": {
          "uds.diag_addr_source": "0x1032",
          "uds.diag_addr_source_name": "4146",
          "uds.diag_addr": "0x1032",
          "uds.diag_addr_name": "4146",
          "uds.diag_addr_target": "0x0e00",
          "uds.diag_addr_target_name": "3584",
          "uds.diag_addr": "0x0e00",
          "uds.diag_addr_name": "3584",
          "uds.sid": "0x3e",
          "uds.reply": "0x01",
          "uds.subfunction": "0x80",
          "uds.subfunction_tree": {
            "uds.tp.subfunction_without_suppress": "0x00"
          }
        }
      }
    }
  },
  {
    "_index": "packets-2024-09-12",
    "_type": "doc",
    "_score": null,
    "_source": {
      "layers": {
        "frame": {
          "frame.encap_type": "1",
          "frame.time": "Sep 12, 2024 16:46:02.009227000 W. Europe Daylight Time",
          "frame.time_utc": "Sep 12, 2024 14:46:02.009227000 UTC",
          "frame.time_epoch": "1726152362.009227000",
          "frame.offset_shift": "0.000000000",
          "frame.time_delta": "0.000217000",
          "frame.time_delta_displayed": "0.000285000",
          "frame.time_relative": "1.782337000",
          "frame.number": "156",
          "frame.len": "81",
          "frame.cap_len": "81",
          "frame.marked": "0",
          "frame.ignored": "0",
          "frame.protocols": "eth:ethertype:ip:tcp:doip:uds",
          "frame.coloring_rule.name": "TCP",
          "frame.coloring_rule.string": "tcp"
        },
        "eth": {
          "eth.dst": "00:00:00:00:00:00",
          "eth.dst_tree": {
            "eth.dst_resolved": "00:00:00_00:00:00",
            "eth.dst.oui": "0",
            "eth.dst.oui_resolved": "Officially Xerox, but 0:0:0:0:0:0 is more common",
            "eth.dst.lg": "0",
            "eth.dst.ig": "0",
            "eth.addr": "00:00:00:00:00:00",
            "eth.addr_resolved": "00:00:00_00:00:00",
            "eth.addr.oui": "0",
            "eth.addr.oui_resolved": "Officially Xerox, but 0:0:0:0:0:0 is more common",
            "eth.lg": "0",
            "eth.ig": "0"
          },
          "eth.src": "00:00:00:00:00:00",
          "eth.src_tree": {
            "eth.src_resolved": "00:00:00_00:00:00",
            "eth.src.oui": "0",
            "eth.src.oui_resolved": "Officially Xerox, but 0:0:0:0:0:0 is more common",
            "eth.src.lg": "0",
            "eth.src.ig": "0",
            "eth.addr": "00:00:00:00:00:00",
            "eth.addr_resolved": "00:00:00_00:00:00",
            "eth.addr.oui": "0",
            "eth.addr.oui_resolved": "Officially Xerox, but 0:0:0:0:0:0 is more common",
            "eth.lg": "0",
            "eth.ig": "0"
          },
          "eth.type": "0x0800",
          "eth.stream": "0"
        },
        "ip": {
          "ip.version": "4",
          "ip.hdr_len": "20",
          "ip.dsfield": "0x00",
          "ip.dsfield_tree": {
            "ip.dsfield.dscp": "0",
            "ip.dsfield.ecn": "0"
          },
          "ip.len": "67",
          "ip.id": "0x3bf7",
          "ip.flags": "0x02",
          "ip.flags_tree": {
            "ip.flags.rb": "0",
            "ip.flags.df": "1",
            "ip.flags.mf": "0"
          },
          "ip.frag_offset": "0",
          "ip.ttl": "64",
          "ip.proto": "6",
          "ip.checksum": "0x00bc",
          "ip.checksum.status": "1",
          "ip.checksum_calculated": "0x00bc",
          "ip.src": "127.0.0.1",
          "ip.addr": "127.0.0.1",
          "ip.src_host": "kubernetes.docker.internal",
          "ip.host": "kubernetes.docker.internal",
          "ip.dst": "127.0.0.1",
          "ip.addr": "127.0.0.1",
          "ip.dst_host": "kubernetes.docker.internal",
          "ip.host": "kubernetes.docker.internal",
          "ip.stream": "0"
        },
        "tcp": {
          "tcp.srcport": "43208",
          "tcp.dstport": "13400",
          "tcp.port": "43208",
          "tcp.port": "13400",
          "tcp.stream": "2",
          "tcp.stream.pnum": "16",
          "tcp.completeness": "31",
          "tcp.completeness_tree": {
            "tcp.completeness.rst": "0",
            "tcp.completeness.fin": "1",
            "tcp.completeness.data": "1",
            "tcp.completeness.ack": "1",
            "tcp.completeness.syn-ack": "1",
            "tcp.completeness.syn": "1",
            "tcp.completeness.str": "·FDASS"
          },
          "tcp.len": "15",
          "tcp.seq": "3549143286",
          "tcp.seq_raw": "3549143286",
          "tcp.nxtseq": "3549143301",
          "tcp.ack": "1622714265",
          "tcp.ack_raw": "1622714265",
          "tcp.hdr_len": "32",
          "tcp.flags": "0x0018",
          "tcp.flags_tree": {
            "tcp.flags.res": "0",
            "tcp.flags.ae": "0",
            "tcp.flags.cwr": "0",
            "tcp.flags.ece": "0",
            "tcp.flags.urg": "0",
            "tcp.flags.ack": "1",
            "tcp.flags.push": "1",
            "tcp.flags.reset": "0",
            "tcp.flags.syn": "0",
            "tcp.flags.fin": "0",
            "tcp.flags.str": "·······AP···"
          },
          "tcp.window_size_value": "512",
          "tcp.window_size": "65536",
          "tcp.window_size_scalefactor": "128",
          "tcp.checksum": "0xfe37",
          "tcp.checksum.status": "2",
          "tcp.urgent_pointer": "0",
          "tcp.options": "01:01:08:0a:cd:d9:d7:2a:cd:d9:d7:28",
          "tcp.options_tree": {
            "tcp.options.nop": "01",
            "tcp.options.nop_tree": {
              "tcp.option_kind": "1"
            },
            "tcp.options.nop": "01",
            "tcp.options.nop_tree": {
              "tcp.option_kind": "1"
            },
            "tcp.options.timestamp": "08:0a:cd:d9:d7:2a:cd:d9:d7:28",
            "tcp.options.timestamp_tree": {
              "tcp.option_kind": "8",
              "tcp.option_len": "10",
              "tcp.options.timestamp.tsval": "3453605674",
              "tcp.options.timestamp.tsecr": "3453605672"
            }
          },
          "Timestamps": {
            "tcp.time_relative": "0.021064000",
            "tcp.time_delta": "0.000217000"
          },
          "tcp.payload": "02:fd:80:01:00:00:00:07:0e:00:10:32:22:f1:90",
          "tcp.pdu.size": "15"
        },
        "doip": {
          "Header": {
            "doip.version": "0x02",
            "doip.inverse": "0xfd",
            "doip.type": "0x8001",
            "doip.length": "7"
          },
          "doip.source_address": "0x0e00",
          "doip.target_address": "0x1032"
        },
        "uds": {
          "uds.diag_addr_source": "0x0e00",
          "uds.diag_addr_source_name": "3584",
          "uds.diag_addr": "0x0e00",
          "uds.diag_addr_name": "3584",
          "uds.diag_addr_target": "0x1032",
          "uds.diag_addr_target_name": "4146",
          "uds.diag_addr": "0x1032",
          "uds.diag_addr_name": "4146",
          "uds.sid": "0x22",
          "uds.reply": "0x00",
          "uds.rdbi.data_identifier": "0xf190"
        }
      }
    }
  },
  {
    "_index": "packets-2024-09-12",
    "_type": "doc",
    "_score": null,
    "_source": {
      "layers": {
        "frame": {
          "frame.encap_type": "1",
          "frame.time": "Sep 12, 2024 16:46:02.012759000 W. Europe Daylight Time",
          "frame.time_utc": "Sep 12, 2024 14:46:02.012759000 UTC",
          "frame.time_epoch": "1726152362.012759000",
          "frame.offset_shift": "0.000000000",
          "frame.time_delta": "0.000503000",
          "frame.time_delta_displayed": "0.003532000",
          "frame.time_relative": "1.785869000",
          "frame.number": "162",
          "frame.len": "81",
          "frame.cap_len": "81",
          "frame.marked": "0",
          "frame.ignored": "0",
          "frame.protocols": "eth:ethertype:ip:tcp:doip:uds",
          "frame.coloring_rule.name": "TCP",
          "frame.coloring_rule.string": "tcp"
        },
        "eth": {
          "eth.dst": "00:00:00:00:00:00",
          "eth.dst_tree": {
            "eth.dst_resolved": "00:00:00_00:00:00",
            "eth.dst.oui": "0",
            "eth.dst.oui_resolved": "Officially Xerox, but 0:0:0:0:0:0 is more common",
            "eth.dst.lg": "0",
            "eth.dst.ig": "0",
            "eth.addr": "00:00:00:00:00:00",
            "eth.addr_resolved": "00:00:00_00:00:00",
            "eth.addr.oui": "0",
            "eth.addr.oui_resolved": "Officially Xerox, but 0:0:0:0:0:0 is more common",
            "eth.lg": "0",
            "eth.ig": "0"
          },
          "eth.src": "00:00:00:00:00:00",
          "eth.src_tree": {
            "eth.src_resolved": "00:00:00_00:00:00",
            "eth.src.oui": "0",
            "eth.src.oui_resolved": "Officially Xerox, but 0:0:0:0:0:0 is more common",
            "eth.src.lg": "0",
            "eth.src.ig": "0",
            "eth.addr": "00:00:00:00:00:00",
            "eth.addr_resolved": "00:00:00_00:00:00",
            "eth.addr.oui": "0",
            "eth.addr.oui_resolved": "Officially Xerox, but 0:0:0:0:0:0 is more common",
            "eth.lg": "0",
            "eth.ig": "0"
          },
          "eth.type": "0x0800",
          "eth.stream": "0"
        },
        "ip": {
          "ip.version": "4",
          "ip.hdr_len": "20",
          "ip.dsfield": "0x00",
          "ip.dsfield_tree": {
            "ip.dsfield.dscp": "0",
            "ip.dsfield.ecn": "0"
          },
          "ip.len": "67",
          "ip.id": "0x4cc5",
          "ip.flags": "0x02",
          "ip.flags_tree": {
            "ip.flags.rb": "0",
            "ip.flags.df": "1",
            "ip.flags.mf": "0"
          },
          "ip.frag_offset": "0",
          "ip.ttl": "64",
          "ip.proto": "6",
          "ip.checksum": "0xefed",
          "ip.checksum.status": "1",
          "ip.checksum_calculated": "0xefed",
          "ip.src": "127.0.0.1",
          "ip.addr": "127.0.0.1",
          "ip.src_host": "kubernetes.docker.internal",
          "ip.host": "kubernetes.docker.internal",
          "ip.dst": "127.0.0.1",
          "ip.addr": "127.0.0.1",
          "ip.dst_host": "kubernetes.docker.internal",
          "ip.host": "kubernetes.docker.internal",
          "ip.stream": "0"
        },
        "tcp": {
          "tcp.srcport": "13400",
          "tcp.dstport": "43208",
          "tcp.port": "13400",
          "tcp.port": "43208",
          "tcp.stream": "2",
          "tcp.stream.pnum": "18",
          "tcp.completeness": "31",
          "tcp.completeness_tree": {
            "tcp.completeness.rst": "0",
            "tcp.completeness.fin": "1",
            "tcp.completeness.data": "1",
            "tcp.completeness.ack": "1",
            "tcp.completeness.syn-ack": "1",
            "tcp.completeness.syn": "1",
            "tcp.completeness.str": "·FDASS"
          },
          "tcp.len": "15",
          "tcp.seq": "1622714278",
          "tcp.seq_raw": "1622714278",
          "tcp.nxtseq": "1622714293",
          "tcp.ack": "3549143301",
          "tcp.ack_raw": "3549143301",
          "tcp.hdr_len": "32",
          "tcp.flags": "0x0018",
          "tcp.flags_tree": {
            "tcp.flags.res": "0",
            "tcp.flags.ae": "0",
            "tcp.flags.cwr": "0",
            "tcp.flags.ece": "0",
            "tcp.flags.urg": "0",
            "tcp.flags.ack": "1",
            "tcp.flags.push": "1",
            "tcp.flags.reset": "0",
            "tcp.flags.syn": "0",
            "tcp.flags.fin": "0",
            "tcp.flags.str": "·······AP···"
          },
          "tcp.window_size_value": "512",
          "tcp.window_size": "65536",
          "tcp.window_size_scalefactor": "128",
          "tcp.checksum": "0xfe37",
          "tcp.checksum.status": "2",
          "tcp.urgent_pointer": "0",
          "tcp.options": "01:01:08:0a:cd:d9:d7:2e:cd:d9:d7:2a",
          "tcp.options_tree": {
            "tcp.options.nop": "01",
            "tcp.options.nop_tree": {
              "tcp.option_kind": "1"
            },
            "tcp.options.nop": "01",
            "tcp.options.nop_tree": {
              "tcp.option_kind": "1"
            },
            "tcp.options.timestamp": "08:0a:cd:d9:d7:2e:cd:d9:d7:2a",
            "tcp.options.timestamp_tree": {
              "tcp.option_kind": "8",
              "tcp.option_len": "10",
              "tcp.options.timestamp.tsval": "3453605678",
              "tcp.options.timestamp.tsecr": "3453605674"
            }
          },
          "Timestamps": {
            "tcp.time_relative": "0.024596000",
            "tcp.time_delta": "0.001823000"
          },
          "tcp.payload": "02:fd:80:01:00:00:00:07:10:32:0e:00:7f:10:10",
          "tcp.pdu.size": "15"
        },
        "doip": {
          "Header": {
            "doip.version": "0x02",
            "doip.inverse": "0xfd",
            "doip.type": "0x8001",
            "doip.length": "7"
          },
          "doip.source_address": "0x1032",
          "doip.target_address": "0x0e00"
        },
        "uds": {
          "uds.diag_addr_source": "0x1032",
          "uds.diag_addr_source_name": "4146",
          "uds.diag_addr": "0x1032",
          "uds.diag_addr_name": "4146",
          "uds.diag_addr_target": "0x0e00",
          "uds.diag_addr_target_name": "3584",
          "uds.diag_addr": "0x0e00",
          "uds.diag_addr_name": "3584",
          "uds.sid": "0x3f",
          "uds.reply": "0x01",
          "uds.err.sid": "0x10",
          "uds.err.code": "0x10"
        }
      }
    }
  }
]
